starcode_labyrinth/drawing.py
starcode_labyrinth/feedback.py
starcode_labyrinth/logic.py
starcode_labyrinth/state.py
starcode_labyrinth-0.2.0.dist-info/LICENSE.md
starcode_labyrinth-0.2.0.dist-info/METADATA
starcode_labyrinth-0.2.0.dist-info/WHEEL
starcode_labyrinth-0.2.0.dist-info/top_level.txt
starcode_labyrinth-0.2.0.dist-info/RECORD
