Metadata-Version: 2.1
Name: starcode-labyrinth
Version: 0.2.0
Summary: A module to draw labyrinth maps and navigate through them. This is intended for teaching.
Home-page: https://gitlab.com/bpaassen/starcode_labyrinth
Author: Benjamin Paassen
Author-email: benjamin.paassen@dfki.de
Keywords: labyrinth finite-state-automata finite-state-machines
Classifier: Programming Language :: Python :: 3
Classifier: License :: OSI Approved :: GNU General Public License v3 (GPLv3)
Classifier: Operating System :: OS Independent
License-File: LICENSE.md
Requires-Dist: numpy
Requires-Dist: matplotlib
